xdcc/__init__.py
xdcc/__main__.py
xdcc/xdcc.py
xdcc-0.0.3.dist-info/LICENSE
xdcc-0.0.3.dist-info/METADATA
xdcc-0.0.3.dist-info/WHEEL
xdcc-0.0.3.dist-info/entry_points.txt
xdcc-0.0.3.dist-info/top_level.txt
xdcc-0.0.3.dist-info/RECORD
