Metadata-Version: 2.1
Name: xdcc
Version: 0.0.3
Summary: A simple XDCC downloader written in python3
Home-page: https://github.com/thiagotps/xdcc
Author: Thiago T. P. Silva
Author-email: thiagoteodoro501@gmail.com
License: UNKNOWN
Keywords: irc xdcc
Platform: UNKNOWN
Classifier: Programming Language :: Python :: 3
Classifier: License :: OSI Approved :: MIT License
Classifier: Operating System :: OS Independent
Requires-Python: >=3.7
Requires-Dist: irc
